silver_octo_potato/__init__.py
silver_octo_potato/example.py
silver_octo_potato-0.2.9.dist-info/LICENSE
silver_octo_potato-0.2.9.dist-info/METADATA
silver_octo_potato-0.2.9.dist-info/WHEEL
silver_octo_potato-0.2.9.dist-info/RECORD
